doctoshotgun/__init__.py
doctoshotgun/__main__.py
doctoshotgun/cli.py
doctoshotgun/doctolib.py
doctoshotgun/exceptions.py
doctoshotgun/tools.py
doctoshotgun-1.0.1.dist-info/COPYING
doctoshotgun-1.0.1.dist-info/METADATA
doctoshotgun-1.0.1.dist-info/WHEEL
doctoshotgun-1.0.1.dist-info/entry_points.txt
doctoshotgun-1.0.1.dist-info/top_level.txt
doctoshotgun-1.0.1.dist-info/RECORD
