Metadata-Version: 2.1
Name: doctoshotgun
Version: 1.0.1
Summary: Book vaccine slots on Doctolib
Home-page: https://doctoshotgun.com
Author: Romain Bignon
Author-email: romain@doctoshotgun.com
Maintainer: Romain Bignon
Maintainer-email: romain@doctoshotgun.com
License: GNU GPL 3
Keywords: vaccine,covid19
Platform: UNKNOWN
Classifier: Environment :: Console
Classifier: License :: OSI Approved :: GNU General Public License v3 or later (GPLv3+)
Classifier: Programming Language :: Python
Classifier: Programming Language :: Python :: 3
Classifier: Programming Language :: Python :: 3.6
Classifier: Programming Language :: Python :: 3.7
Classifier: Programming Language :: Python :: 3.8
Classifier: Programming Language :: Python :: 3.9
Classifier: Programming Language :: Python :: 3.10
Classifier: Programming Language :: Python :: 3 :: Only
Classifier: Topic :: Internet :: WWW/HTTP
Classifier: Topic :: Internet :: WWW/HTTP :: Browsers
Requires-Python: >=3.6
License-File: COPYING
Requires-Dist: woob
Requires-Dist: cloudscraper
Requires-Dist: python-dateutil
Requires-Dist: termcolor
Requires-Dist: colorama
